flake8_no_nested_comprehensions.py
flake8_no_nested_comprehensions-1.0.0.dist-info/LICENSE
flake8_no_nested_comprehensions-1.0.0.dist-info/METADATA
flake8_no_nested_comprehensions-1.0.0.dist-info/WHEEL
flake8_no_nested_comprehensions-1.0.0.dist-info/entry_points.txt
flake8_no_nested_comprehensions-1.0.0.dist-info/top_level.txt
flake8_no_nested_comprehensions-1.0.0.dist-info/RECORD
