Metadata-Version: 2.1
Name: flake8_no_nested_comprehensions
Version: 1.0.0
Summary: A flake8 plugin to disallow nested comprehensions
Author-email: Timmy Welch <timmy@narnian.us>
License: MIT
Project-URL: Homepage, https://github.com/lordwelch/flake8_no_nested_comprehensions
Classifier: License :: OSI Approved :: MIT License
Classifier: Programming Language :: Python :: 3
Classifier: Programming Language :: Python :: 3 :: Only
Classifier: Programming Language :: Python :: Implementation :: CPython
Classifier: Programming Language :: Python :: Implementation :: PyPy
Requires-Python: >=3.9
License-File: LICENSE
Requires-Dist: flake8 >4
